setup.py
peewee_manager.egg-info/PKG-INFO
peewee_manager.egg-info/SOURCES.txt
peewee_manager.egg-info/dependency_links.txt
peewee_manager.egg-info/requires.txt
peewee_manager.egg-info/top_level.txt
peeweemgr/__init__.py
peeweemgr/database.py