Metadata-Version: 1.1
Name: peewee-manager
Version: 1.0
Summary: peewee database connection manager
Home-page: https://github.com/mqingyn/peewee_manager
Author: mqingyn
Author-email: mqingyn@gmail.com
License: MIT
Keywords: python peewee db
Platform: UNKNOWN
Classifier: Development Status :: 5 - Production/Stable
Classifier: License :: OSI Approved :: BSD License
Classifier: Programming Language :: Python :: 2
Classifier: Programming Language :: Python :: 2.6
Classifier: Programming Language :: Python :: 2.7
Classifier: Programming Language :: Python :: Implementation :: CPython
Classifier: Programming Language :: Python :: Implementation :: PyPy
Requires: peewee
